nslocalizer/__init__.py
nslocalizer/main.py
nslocalizer/version.py
nslocalizer/version_info.py
nslocalizer/Executor/Executor.py
nslocalizer/Executor/__init__.py
nslocalizer/Finder/CodeFinder.py
nslocalizer/Finder/LanguageFinder.py
nslocalizer/Finder/PathFinder.py
nslocalizer/Finder/__init__.py
nslocalizer/Helpers/FileOperations.py
nslocalizer/Helpers/Logger.py
nslocalizer/Helpers/Switch.py
nslocalizer/Helpers/__init__.py
nslocalizer/Helpers/xcrun.py
nslocalizer/Language/Language.py
nslocalizer/Language/LanguageString.py
nslocalizer/Language/__init__.py
nslocalizer/Reporter/Reporter.py
nslocalizer/Reporter/__init__.py
nslocalizer/xcodeproj/__init__.py
nslocalizer/xcodeproj/xcodeproj.py
nslocalizer/xcodeproj/pbProj/PBXAggregateTarget.py
nslocalizer/xcodeproj/pbProj/PBXAppleScriptBuildPhase.py
nslocalizer/xcodeproj/pbProj/PBXApplicationReference.py
nslocalizer/xcodeproj/pbProj/PBXApplicationTarget.py
nslocalizer/xcodeproj/pbProj/PBXBuildFile.py
nslocalizer/xcodeproj/pbProj/PBXBuildRule.py
nslocalizer/xcodeproj/pbProj/PBXBundleReference.py
nslocalizer/xcodeproj/pbProj/PBXBundleTarget.py
nslocalizer/xcodeproj/pbProj/PBXContainerItemProxy.py
nslocalizer/xcodeproj/pbProj/PBXCopyFilesBuildPhase.py
nslocalizer/xcodeproj/pbProj/PBXExecutableFileReference.py
nslocalizer/xcodeproj/pbProj/PBXFileReference.py
nslocalizer/xcodeproj/pbProj/PBXFrameworkReference.py
nslocalizer/xcodeproj/pbProj/PBXFrameworkTarget.py
nslocalizer/xcodeproj/pbProj/PBXFrameworksBuildPhase.py
nslocalizer/xcodeproj/pbProj/PBXGroup.py
nslocalizer/xcodeproj/pbProj/PBXHeadersBuildPhase.py
nslocalizer/xcodeproj/pbProj/PBXItem.py
nslocalizer/xcodeproj/pbProj/PBXJavaArchiveBuildPhase.py
nslocalizer/xcodeproj/pbProj/PBXLegacyTarget.py
nslocalizer/xcodeproj/pbProj/PBXLibraryReference.py
nslocalizer/xcodeproj/pbProj/PBXLibraryTarget.py
nslocalizer/xcodeproj/pbProj/PBXNativeTarget.py
nslocalizer/xcodeproj/pbProj/PBXProject.py
nslocalizer/xcodeproj/pbProj/PBXReferenceProxy.py
nslocalizer-1.0.2.dist-info/LICENSE
nslocalizer-1.0.2.dist-info/METADATA
nslocalizer-1.0.2.dist-info/WHEEL
nslocalizer-1.0.2.dist-info/entry_points.txt
nslocalizer-1.0.2.dist-info/top_level.txt
nslocalizer-1.0.2.dist-info/RECORD
