Metadata-Version: 2.1
Name: nslocalizer
Version: 1.0.2
Summary: Tool for finding missing and unused NSLocalizdStrings
Home-page: https://github.com/samdmarshall/nslocalizer
Author: Samantha Marshall
Author-email: hello@pewpewthespells.com
License: BSD 3-Clause
Platform: UNKNOWN
Requires-Dist: pyobjc-core
Requires-Dist: pyobjc-framework-Cocoa
Requires-Dist: pbPlist
Requires-Dist: langcodes
